Workbook

Sheet README
A1: Casino Betting - QA Manual Test Case Test Pack
A3: Purpose | B3: Provide reusable sample manual test cases across casino platform qa / betting & game flows workflows in a simulated casino platform, including core positive, negative, integration, and end-to-end flows.
A4: How to use | B4: Open each module sheet and update the Status and Notes columns during execution. Summary KPIs and module counts refresh automatically.
A5: Important note | B5: These are sample QA scenarios for portfolio use and should be tailored to the exact casino platform build, jurisdiction rules, payment integrations, and enabled responsible-gaming controls in the target environment.
A6: Default status | B6: Not Run
A7: Default priority | B7: High
A8: Primary domain | B8: Casino Platform QA - Betting & Game Flows
A9: Demo credentials | B9: Simulated Player: player01 / Demo123! | Simulated Admin: qa_admin / Admin123!
A11: Source Name | B11: Path / URL | C11: Use in this workbook
A12: Portfolio README | B12: ../README.md | C12: Overview and scope for this simulated casino QA portfolio
A13: Test Strategy | B13: ../test-strategy/test-approach.md | C13: Risk-based test approach and execution guidance
A14: Postman Collection | B14: ../api-tests/postman-collections/casino-platform-qa.postman_collection.json | C14: API request examples aligned to these scenarios
A15: Sample Requests | B15: ../api-tests/sample-requests.json | C15: Sample payloads aligned to wallet, betting, and compliance flows

Sheet Summary
A1: Casino Betting - QA Manual Test Case Tracker
A3: Manual QA test suite for casino betting and game settlement workflows using the same multi-tab execution-tracker structure as the user's prior OpenMRS-style portfolio trackers.
A5: Workbook Controls
A6: Default Status | B6: Not Run
A7: Default Priority | B7: High
A8: Portfolio Owner | B8: Ramon Tan Jr.
A9: Primary Domain | B9: Casino Platform QA - Betting & Game Flows
A11: Module Coverage
A12: Module | B12: Sheet Name | C12: Total Cases | D12: High Priority | E12: Negative Cases | F12: Automation Candidates
A13: Player Access | B13: 10_Player_Access | C13: =COUNTA('10_Player_Access'!A:A)-2 -> 5 | D13: =COUNTIF('10_Player_Access'!H:H,"Critical")+COUNTIF('10_Player_Access'!H:H,"High") -> 4 | E13: =COUNTIF('10_Player_Access'!I:I,"Negative") -> 1 | F13: =COUNTIF('10_Player_Access'!J:J,"Yes") -> 1
A14: Game Session & Lobby | B14: 20_Game_Session_Lobby | C14: =COUNTA('20_Game_Session_Lobby'!A:A)-2 -> 5 | D14: =COUNTIF('20_Game_Session_Lobby'!H:H,"Critical")+COUNTIF('20_Game_Session_Lobby'!H:H,"High") -> 4 | E14: =COUNTIF('20_Game_Session_Lobby'!I:I,"Negative") -> 1 | F14: =COUNTIF('20_Game_Session_Lobby'!J:J,"Yes") -> 2
A15: Bet Placement | B15: 30_Bet_Placement | C15: =COUNTA('30_Bet_Placement'!A:A)-2 -> 6 | D15: =COUNTIF('30_Bet_Placement'!H:H,"Critical")+COUNTIF('30_Bet_Placement'!H:H,"High") -> 6 | E15: =COUNTIF('30_Bet_Placement'!I:I,"Negative") -> 2 | F15: =COUNTIF('30_Bet_Placement'!J:J,"Yes") -> 3
A16: Settlement & Payouts | B16: 40_Settlement_Payouts | C16: =COUNTA('40_Settlement_Payouts'!A:A)-2 -> 6 | D16: =COUNTIF('40_Settlement_Payouts'!H:H,"Critical")+COUNTIF('40_Settlement_Payouts'!H:H,"High") -> 6 | E16: =COUNTIF('40_Settlement_Payouts'!I:I,"Negative") -> 1 | F16: =COUNTIF('40_Settlement_Payouts'!J:J,"Yes") -> 2
A17: Limits & Error Handling | B17: 50_Limits_Error_Handling | C17: =COUNTA('50_Limits_Error_Handling'!A:A)-2 -> 5 | D17: =COUNTIF('50_Limits_Error_Handling'!H:H,"Critical")+COUNTIF('50_Limits_Error_Handling'!H:H,"High") -> 5 | E17: =COUNTIF('50_Limits_Error_Handling'!I:I,"Negative") -> 2 | F17: =COUNTIF('50_Limits_Error_Handling'!J:J,"Yes") -> 1
A18: Betting End-to-End | B18: 60_Betting_E2E | C18: =COUNTA('60_Betting_E2E'!A:A)-2 -> 4 | D18: =COUNTIF('60_Betting_E2E'!H:H,"Critical")+COUNTIF('60_Betting_E2E'!H:H,"High") -> 4 | E18: =COUNTIF('60_Betting_E2E'!I:I,"Negative") -> 0 | F18: =COUNTIF('60_Betting_E2E'!J:J,"Yes") -> 0
A19: Total | C19: =SUM(C13:C18) -> 31 | D19: =SUM(D13:D18) -> 29 | E19: =SUM(E13:E18) -> 7 | F19: =SUM(F13:F18) -> 9
A22: Execution Status
A23: Status | B23: Count | D23: Metric | E23: Value
A24: Not Run | B24: =COUNTIF('10_Player_Access'!K:K,"Not Run")+COUNTIF('20_Game_Session_Lobby'!K:K,"Not Run")+COUNTIF('30_Bet_Placement'!K:K,"Not Run")+COUNTIF('40_Settlement_Payouts'!K:K,"Not Run")+COUNTIF('50_Limits_Error_Handling'!K:K,"Not Run")+COUNTIF('60_Betting_E2E'!K:K,"Not Run") -> 31 | D24: Total Test Cases | E24: =C19 -> 31
A25: Pass | B25: =COUNTIF('10_Player_Access'!K:K,"Pass")+COUNTIF('20_Game_Session_Lobby'!K:K,"Pass")+COUNTIF('30_Bet_Placement'!K:K,"Pass")+COUNTIF('40_Settlement_Payouts'!K:K,"Pass")+COUNTIF('50_Limits_Error_Handling'!K:K,"Pass")+COUNTIF('60_Betting_E2E'!K:K,"Pass") -> 0 | D25: Executed Cases | E25: =SUM(B25:B27) -> 0
A26: Fail | B26: =COUNTIF('10_Player_Access'!K:K,"Fail")+COUNTIF('20_Game_Session_Lobby'!K:K,"Fail")+COUNTIF('30_Bet_Placement'!K:K,"Fail")+COUNTIF('40_Settlement_Payouts'!K:K,"Fail")+COUNTIF('50_Limits_Error_Handling'!K:K,"Fail")+COUNTIF('60_Betting_E2E'!K:K,"Fail") -> 0 | D26: Execution % | E26: =IFERROR(E25/E24,0) -> 0
A27: Blocked | B27: =COUNTIF('10_Player_Access'!K:K,"Blocked")+COUNTIF('20_Game_Session_Lobby'!K:K,"Blocked")+COUNTIF('30_Bet_Placement'!K:K,"Blocked")+COUNTIF('40_Settlement_Payouts'!K:K,"Blocked")+COUNTIF('50_Limits_Error_Handling'!K:K,"Blocked")+COUNTIF('60_Betting_E2E'!K:K,"Blocked") -> 0 | D27: Pass Rate | E27: =IFERROR(B25/E25,0) -> 0
D28: Fail Rate | E28: =IFERROR(B26/E25,0) -> 0

Sheet 10_Player_Access
A1: Update the Status and Notes columns during execution. Summary KPIs and counts refresh automatically.
A2: TC_ID | B2: Module | C2: Scenario | D2: Preconditions | E2: Steps | F2: Test Data | G2: Expected Result | H2: Priority | I2: Type | J2: Automation Candidate | K2: Status | L2: Notes
A3: BET-AUTH-001 | B3: Player Access | C3: Verified player can enter betting lobby after successful login | D3: Verified player account exists | E3: 1. Log in 2. Open lobby | F3: verified player | G3: Lobby loads with permitted games and current wallet balance | H3: Critical | I3: Positive | J3: Yes | K3: Not Run | L3: Core entry path
A4: BET-AUTH-002 | B4: Player Access | C4: Unverified or restricted player is blocked from restricted games | D4: Restricted player state exists | E4: 1. Log in as restricted player 2. Attempt game entry | F4: restricted player account | G4: System blocks restricted access and shows controlled message | H4: Critical | I4: Security | J4: Later | K4: Not Run | L4: Access restriction
A5: BET-AUTH-003 | B5: Player Access | C5: Expired session redirects player to login before bet placement | D5: Authenticated session expires | E5: 1. Stay idle until timeout 2. Attempt to place bet | F5: expired session | G5: Player is redirected to login and no bet is accepted | H5: High | I5: Security | J5: Later | K5: Not Run | L5: Session expiry
A6: BET-AUTH-004 | B6: Player Access | C6: Lobby does not expose unavailable games configured for another jurisdiction | D6: Game entitlement rules exist | E6: 1. Review lobby as jurisdiction-limited player | F6: jurisdiction-limited profile | G6: Only allowed games are visible and unavailable ones are hidden or disabled | H6: High | I6: Regression | J6: Later | K6: Not Run | L6: Jurisdiction filtering
A7: BET-AUTH-005 | B7: Player Access | C7: Generic error is shown if lobby profile fetch fails | D7: Injected profile fetch failure exists | E7: 1. Open lobby during simulated service error | F7: simulated profile service outage | G7: System shows controlled error and does not present partial or misleading game state | H7: Medium | I7: Negative | J7: Later | K7: Not Run | L7: Graceful degradation

Sheet 20_Game_Session_Lobby
A1: Update the Status and Notes columns during execution. Summary KPIs and counts refresh automatically.
A2: TC_ID | B2: Module | C2: Scenario | D2: Preconditions | E2: Steps | F2: Test Data | G2: Expected Result | H2: Priority | I2: Type | J2: Automation Candidate | K2: Status | L2: Notes
A3: LOB-001 | B3: Game Session & Lobby | C3: Selecting a game launches a session with correct player context | D3: Player is logged in and game is available | E3: 1. Select game 2. Wait for session launch | F3: available slot or table game | G3: Game session starts successfully with correct player and balance context | H3: Critical | I3: Positive | J3: Yes | K3: Not Run | L3: Session launch
A4: LOB-002 | B4: Game Session & Lobby | C4: Launching game with insufficient funds still opens but blocks bet placement according to rules | D4: Player balance is below minimum bet | E4: 1. Launch game 2. Attempt betting | F4: player balance below min bet | G4: Game loads and correctly prevents wagering beyond funds | H4: High | I4: Regression | J4: Later | K4: Not Run | L4: Low-funds behavior
A5: LOB-003 | B5: Game Session & Lobby | C5: Closed or maintenance game cannot be launched from lobby | D5: Target game is in maintenance | E5: 1. View lobby 2. Attempt to open maintenance game | F5: maintenance game tile | G5: Game is unavailable and launch is blocked with clear status | H5: High | I5: Negative | J5: Yes | K5: Not Run | L5: Maintenance state
A6: LOB-004 | B6: Game Session & Lobby | C6: Lobby refresh preserves latest balance after completed wallet activity | D6: Recent wallet update exists | E6: 1. Deposit or settle game externally 2. Refresh lobby | F6: recent balance change | G6: Lobby reflects latest balance without requiring full re-login | H6: High | I6: Integration | J6: Later | K6: Not Run | L6: Balance sync
A7: LOB-005 | B7: Game Session & Lobby | C7: Returning from a game to lobby preserves navigation and filters | D7: Player entered game from filtered lobby | E7: 1. Filter lobby 2. Open game 3. Return to lobby | F7: filter by category/provider | G7: Lobby returns cleanly and previously selected filters remain usable | H7: Medium | I7: Usability | J7: Later | K7: Not Run | L7: Navigation continuity

Sheet 30_Bet_Placement
A1: Update the Status and Notes columns during execution. Summary KPIs and counts refresh automatically.
A2: TC_ID | B2: Module | C2: Scenario | D2: Preconditions | E2: Steps | F2: Test Data | G2: Expected Result | H2: Priority | I2: Type | J2: Automation Candidate | K2: Status | L2: Notes
A3: BET-001 | B3: Bet Placement | C3: Valid bet within limits is accepted and wallet is debited once | D3: Player has active session and sufficient balance | E3: 1. Place valid bet 2. Review balance and bet slip | F3: €5 bet on valid game state | G3: Bet is accepted, wallet debits once, and bet reference is generated | H3: Critical | I3: Positive | J3: Yes | K3: Not Run | L3: Core bet placement
A4: BET-002 | B4: Bet Placement | C4: Bet exceeding available balance is rejected without wallet debit | D4: Player has insufficient balance | E4: 1. Attempt oversized bet | F4: bet > available balance | G4: System rejects bet and wallet balance remains unchanged | H4: Critical | I4: Negative | J4: Yes | K4: Not Run | L4: Funds validation
A5: BET-003 | B5: Bet Placement | C5: Bet exceeding configured table or game limit is blocked | D5: Game limit configuration exists | E5: 1. Enter bet above max limit 2. Submit | F5: bet above table max | G5: System blocks bet with clear limit message | H5: High | I5: Negative | J5: Yes | K5: Not Run | L5: Bet limit rule
A6: BET-004 | B6: Bet Placement | C6: Duplicate submit or network retry does not create duplicate accepted bets | D6: Player is on active betting round | E6: 1. Submit bet 2. Retry during latency or double-click | F6: repeated same bet payload | G6: At most one accepted bet exists for same request id | H6: Critical | I6: Integration | J6: Later | K6: Not Run | L6: Idempotent bet acceptance
A7: BET-005 | B7: Bet Placement | C7: Bonus or promotional funds usage follows configured wagering rules | D7: Player has bonus balance | E7: 1. Place eligible and ineligible bets 2. Review source of funds | F7: bonus wallet player | G7: System uses or blocks bonus funds according to configured rules | H7: High | I7: Regression | J7: Later | K7: Not Run | L7: Bonus fund handling
A8: BET-006 | B8: Bet Placement | C8: Bet payload with invalid game state or stale round id is rejected | D8: Stale or manipulated round id available | E8: 1. Submit bet with stale round id | F8: stale round id payload | G8: System rejects request and records controlled validation failure | H8: Critical | I8: Security | J8: Later | K8: Not Run | L8: Round integrity

Sheet 40_Settlement_Payouts
A1: Update the Status and Notes columns during execution. Summary KPIs and counts refresh automatically.
A2: TC_ID | B2: Module | C2: Scenario | D2: Preconditions | E2: Steps | F2: Test Data | G2: Expected Result | H2: Priority | I2: Type | J2: Automation Candidate | K2: Status | L2: Notes
A3: SET-001 | B3: Settlement & Payouts | C3: Winning bet credits correct payout amount to wallet | D3: Accepted winning bet exists | E3: 1. Settle winning round 2. Review balance and history | F3: winning odds / stake combo | G3: Wallet is credited with correct payout and transaction is logged | H3: Critical | I3: Positive | J3: Yes | K3: Not Run | L3: Winning payout
A4: SET-002 | B4: Settlement & Payouts | C4: Losing bet does not credit wallet and final state is recorded correctly | D4: Accepted losing bet exists | E4: 1. Settle losing round 2. Review balance and history | F4: losing round | G4: No payout is credited and bet record shows final lost status | H4: Critical | I4: Positive | J4: Yes | K4: Not Run | L4: Losing settlement
A5: SET-003 | B5: Settlement & Payouts | C5: Cancelled or voided round restores staked amount exactly once | D5: Accepted bet exists and round voids | E5: 1. Void round 2. Review wallet and bet history | F5: voided round | G5: Stake is returned exactly once with clear void reason | H5: Critical | I5: Integration | J5: Later | K5: Not Run | L5: Void handling
A6: SET-004 | B6: Settlement & Payouts | C6: Partial cash-out amount is calculated and applied correctly | D6: Game supports cash-out feature | E6: 1. Place qualifying bet 2. Trigger partial cash-out | F6: qualifying cash-out scenario | G6: Wallet reflects configured partial payout and remaining exposure updates correctly | H6: High | I6: Regression | J6: Later | K6: Not Run | L6: Cash-out logic
A7: SET-005 | B7: Settlement & Payouts | C7: Late duplicate settlement message does not double-credit payout | D7: One settlement already completed | E7: 1. Replay same settlement event 2. Review wallet and ledger | F7: duplicate settlement event | G7: System ignores or safely handles duplicate settlement without double credit | H7: Critical | I7: Negative | J7: Later | K7: Not Run | L7: Duplicate event handling
A8: SET-006 | B8: Settlement & Payouts | C8: Player history shows accepted, settled, and voided bet statuses accurately | D8: Mixed bet outcomes exist | E8: 1. Open bet history 2. Review recent entries | F8: accepted/won/lost/voided bets | G8: Statuses, stake, payout, and timestamps are accurate for each round | H8: High | I8: Regression | J8: Later | K8: Not Run | L8: History accuracy

Sheet 50_Limits_Error_Handling
A1: Update the Status and Notes columns during execution. Summary KPIs and counts refresh automatically.
A2: TC_ID | B2: Module | C2: Scenario | D2: Preconditions | E2: Steps | F2: Test Data | G2: Expected Result | H2: Priority | I2: Type | J2: Automation Candidate | K2: Status | L2: Notes
A3: LIM-001 | B3: Limits & Error Handling | C3: Session loss limit blocks further bets after threshold is reached | D3: Player account has configured loss limit | E3: 1. Reach limit through settled losses 2. Attempt another bet | F3: player at loss limit | G3: System blocks additional bets and shows responsible-gaming limit message | H3: Critical | I3: Negative | J3: Later | K3: Not Run | L3: Loss limit enforcement
A4: LIM-002 | B4: Limits & Error Handling | C4: Round processing service error returns controlled message without wallet corruption | D4: Injected round-service failure exists | E4: 1. Submit bet during simulated outage | F4: simulated round processing outage | G4: User sees controlled retry/error message and no inconsistent debit occurs | H4: Critical | I4: Negative | J4: Later | K4: Not Run | L4: Failure containment
A5: LIM-003 | B5: Limits & Error Handling | C5: Game session reconnect resumes safely after transient network drop | D5: Player has active session and network interruption is simulated | E5: 1. Disconnect network briefly 2. Reconnect 3. Review session state | F5: transient disconnect | G5: Session recovers safely and player state remains consistent | H5: High | I5: Regression | J5: Later | K5: Not Run | L5: Reconnect behavior
A6: LIM-004 | B6: Limits & Error Handling | C6: Client-side tampering of stake payload is rejected by backend validation | D6: Manipulated client request is possible in test environment | E6: 1. Modify payload amount before submit | F6: tampered stake payload | G6: Backend rejects tampered request and no unauthorized bet is accepted | H6: Critical | I6: Security | J6: Yes | K6: Not Run | L6: Server-side validation
A7: LIM-005 | B7: Limits & Error Handling | C7: Unexpected invalid action returns user-safe error instead of stack trace | D7: Unsupported workflow state is triggered | E7: 1. Force invalid action 2. Observe response | F7: invalid workflow state | G7: System returns user-safe error and logs technical details internally | H7: High | I7: Usability | J7: Later | K7: Not Run | L7: Graceful error handling

Sheet 60_Betting_E2E
A1: Update the Status and Notes columns during execution. Summary KPIs and counts refresh automatically.
A2: TC_ID | B2: Module | C2: Scenario | D2: Preconditions | E2: Steps | F2: Test Data | G2: Expected Result | H2: Priority | I2: Type | J2: Automation Candidate | K2: Status | L2: Notes
A3: BET-E2E-001 | B3: Betting End-to-End | C3: Login to game launch to accepted winning bet flow works end-to-end | D3: Verified funded player exists | E3: 1. Log in 2. Open game 3. Place valid bet 4. Settle as win | F3: funded verified player / winning round | G3: Bet is accepted and payout is credited correctly across full workflow | H3: Critical | I3: E2E | J3: Later | K3: Not Run | L3: Winning journey
A4: BET-E2E-002 | B4: Betting End-to-End | C4: Login to bet rejection due to insufficient balance works end-to-end | D4: Low-balance player exists | E4: 1. Log in 2. Open game 3. Attempt oversized bet | F4: low balance player | G4: System blocks bet cleanly and wallet remains unchanged end-to-end | H4: Critical | I4: E2E | J4: Later | K4: Not Run | L4: Insufficient funds journey
A5: BET-E2E-003 | B5: Betting End-to-End | C5: Placed bet to voided settlement to refunded wallet flow works end-to-end | D5: Player has funded wallet and void scenario | E5: 1. Place bet 2. Void round 3. Review history | F5: voided round flow | G5: Stake is returned once and histories remain consistent end-to-end | H5: Critical | I5: E2E | J5: Later | K5: Not Run | L5: Void lifecycle
A6: BET-E2E-004 | B6: Betting End-to-End | C6: Responsible-gaming limit reached blocks new wagering end-to-end | D6: Player is near configured loss or session limit | E6: 1. Reach limit 2. Attempt new bet | F6: player near responsible-gaming limit | G6: System blocks further wagering and records limit event end-to-end | H6: Critical | I6: E2E | J6: Later | K6: Not Run | L6: Limit enforcement journey
