Workbook

Sheet README
A1: Casino Wallet - QA Manual Test Case Test Pack
A3: Purpose | B3: Provide reusable sample manual test cases across casino platform qa / wallet & payments workflows in a simulated casino platform, including core positive, negative, integration, and end-to-end flows.
A4: How to use | B4: Open each module sheet and update the Status and Notes columns during execution. Summary KPIs and module counts refresh automatically.
A5: Important note | B5: These are sample QA scenarios for portfolio use and should be tailored to the exact casino platform build, jurisdiction rules, payment integrations, and enabled responsible-gaming controls in the target environment.
A6: Default status | B6: Not Run
A7: Default priority | B7: High
A8: Primary domain | B8: Casino Platform QA - Wallet & Payments
A9: Demo credentials | B9: Simulated Player: player01 / Demo123! | Simulated Admin: qa_admin / Admin123!
A11: Source Name | B11: Path / URL | C11: Use in this workbook
A12: Portfolio README | B12: ../README.md | C12: Overview and scope for this simulated casino QA portfolio
A13: Test Strategy | B13: ../test-strategy/test-approach.md | C13: Risk-based test approach and execution guidance
A14: Postman Collection | B14: ../api-tests/postman-collections/casino-platform-qa.postman_collection.json | C14: API request examples aligned to these scenarios
A15: Sample Requests | B15: ../api-tests/sample-requests.json | C15: Sample payloads aligned to wallet, betting, and compliance flows

Sheet Summary
A1: Casino Wallet - QA Manual Test Case Tracker
A3: Manual QA test suite for casino wallet and payment workflows using the same multi-tab execution-tracker structure as the user's prior OpenMRS-style portfolio trackers.
A5: Workbook Controls
A6: Default Status | B6: Not Run
A7: Default Priority | B7: High
A8: Portfolio Owner | B8: Ramon Tan Jr.
A9: Primary Domain | B9: Casino Platform QA - Wallet & Payments
A11: Module Coverage
A12: Module | B12: Sheet Name | C12: Total Cases | D12: High Priority | E12: Negative Cases | F12: Automation Candidates
A13: Wallet Account Access | B13: 10_Wallet_Account_Access | C13: =COUNTA('10_Wallet_Account_Access'!A:A)-2 -> 6 | D13: =COUNTIF('10_Wallet_Account_Access'!H:H,"Critical")+COUNTIF('10_Wallet_Account_Access'!H:H,"High") -> 6 | E13: =COUNTIF('10_Wallet_Account_Access'!I:I,"Negative") -> 2 | F13: =COUNTIF('10_Wallet_Account_Access'!J:J,"Yes") -> 3
A14: Deposit Flows | B14: 20_Deposit_Flows | C14: =COUNTA('20_Deposit_Flows'!A:A)-2 -> 6 | D14: =COUNTIF('20_Deposit_Flows'!H:H,"Critical")+COUNTIF('20_Deposit_Flows'!H:H,"High") -> 6 | E14: =COUNTIF('20_Deposit_Flows'!I:I,"Negative") -> 3 | F14: =COUNTIF('20_Deposit_Flows'!J:J,"Yes") -> 3
A15: Withdrawal Flows | B15: 30_Withdrawal_Flows | C15: =COUNTA('30_Withdrawal_Flows'!A:A)-2 -> 6 | D15: =COUNTIF('30_Withdrawal_Flows'!H:H,"Critical")+COUNTIF('30_Withdrawal_Flows'!H:H,"High") -> 5 | E15: =COUNTIF('30_Withdrawal_Flows'!I:I,"Negative") -> 2 | F15: =COUNTIF('30_Withdrawal_Flows'!J:J,"Yes") -> 2
A16: Transfer & Refunds | B16: 40_Transfer_Refunds | C16: =COUNTA('40_Transfer_Refunds'!A:A)-2 -> 5 | D16: =COUNTIF('40_Transfer_Refunds'!H:H,"Critical")+COUNTIF('40_Transfer_Refunds'!H:H,"High") -> 4 | E16: =COUNTIF('40_Transfer_Refunds'!I:I,"Negative") -> 1 | F16: =COUNTIF('40_Transfer_Refunds'!J:J,"Yes") -> 1
A17: Balance & Reconciliation | B17: 50_Balance_Reconciliation | C17: =COUNTA('50_Balance_Reconciliation'!A:A)-2 -> 5 | D17: =COUNTIF('50_Balance_Reconciliation'!H:H,"Critical")+COUNTIF('50_Balance_Reconciliation'!H:H,"High") -> 5 | E17: =COUNTIF('50_Balance_Reconciliation'!I:I,"Negative") -> 1 | F17: =COUNTIF('50_Balance_Reconciliation'!J:J,"Yes") -> 0
A18: Wallet End-to-End | B18: 60_Wallet_E2E | C18: =COUNTA('60_Wallet_E2E'!A:A)-2 -> 4 | D18: =COUNTIF('60_Wallet_E2E'!H:H,"Critical")+COUNTIF('60_Wallet_E2E'!H:H,"High") -> 4 | E18: =COUNTIF('60_Wallet_E2E'!I:I,"Negative") -> 0 | F18: =COUNTIF('60_Wallet_E2E'!J:J,"Yes") -> 0
A19: Total | C19: =SUM(C13:C18) -> 32 | D19: =SUM(D13:D18) -> 30 | E19: =SUM(E13:E18) -> 9 | F19: =SUM(F13:F18) -> 9
A22: Execution Status
A23: Status | B23: Count | D23: Metric | E23: Value
A24: Not Run | B24: =COUNTIF('10_Wallet_Account_Access'!K:K,"Not Run")+COUNTIF('20_Deposit_Flows'!K:K,"Not Run")+COUNTIF('30_Withdrawal_Flows'!K:K,"Not Run")+COUNTIF('40_Transfer_Refunds'!K:K,"Not Run")+COUNTIF('50_Balance_Reconciliation'!K:K,"Not Run")+COUNTIF('60_Wallet_E2E'!K:K,"Not Run") -> 32 | D24: Total Test Cases | E24: =C19 -> 32
A25: Pass | B25: =COUNTIF('10_Wallet_Account_Access'!K:K,"Pass")+COUNTIF('20_Deposit_Flows'!K:K,"Pass")+COUNTIF('30_Withdrawal_Flows'!K:K,"Pass")+COUNTIF('40_Transfer_Refunds'!K:K,"Pass")+COUNTIF('50_Balance_Reconciliation'!K:K,"Pass")+COUNTIF('60_Wallet_E2E'!K:K,"Pass") -> 0 | D25: Executed Cases | E25: =SUM(B25:B27) -> 0
A26: Fail | B26: =COUNTIF('10_Wallet_Account_Access'!K:K,"Fail")+COUNTIF('20_Deposit_Flows'!K:K,"Fail")+COUNTIF('30_Withdrawal_Flows'!K:K,"Fail")+COUNTIF('40_Transfer_Refunds'!K:K,"Fail")+COUNTIF('50_Balance_Reconciliation'!K:K,"Fail")+COUNTIF('60_Wallet_E2E'!K:K,"Fail") -> 0 | D26: Execution % | E26: =IFERROR(E25/E24,0) -> 0
A27: Blocked | B27: =COUNTIF('10_Wallet_Account_Access'!K:K,"Blocked")+COUNTIF('20_Deposit_Flows'!K:K,"Blocked")+COUNTIF('30_Withdrawal_Flows'!K:K,"Blocked")+COUNTIF('40_Transfer_Refunds'!K:K,"Blocked")+COUNTIF('50_Balance_Reconciliation'!K:K,"Blocked")+COUNTIF('60_Wallet_E2E'!K:K,"Blocked") -> 0 | D27: Pass Rate | E27: =IFERROR(B25/E25,0) -> 0
D28: Fail Rate | E28: =IFERROR(B26/E25,0) -> 0

Sheet 10_Wallet_Account_Access
A1: Update the Status and Notes columns during execution. Summary KPIs and counts refresh automatically.
A2: TC_ID | B2: Module | C2: Scenario | D2: Preconditions | E2: Steps | F2: Test Data | G2: Expected Result | H2: Priority | I2: Type | J2: Automation Candidate | K2: Status | L2: Notes
A3: WAL-AUTH-001 | B3: Wallet Account Access | C3: Valid player login succeeds with correct credentials and 2FA challenge completed | D3: Player account exists and is active | E3: 1. Open player login 2. Enter valid credentials 3. Complete 2FA 4. Submit | F3: player01 / valid password / valid OTP | G3: Player is authenticated successfully and wallet home page loads | H3: Critical | I3: Positive | J3: Yes | K3: Not Run | L3: Core wallet access
A4: WAL-AUTH-002 | B4: Wallet Account Access | C4: Login is blocked with invalid password | D4: Player account exists | E4: 1. Open login 2. Enter valid username and invalid password 3. Submit | F4: player01 / wrong password | G4: System blocks login and shows generic authentication error without granting access | H4: High | I4: Negative | J4: Yes | K4: Not Run | L4: Credential validation
A5: WAL-AUTH-003 | B5: Wallet Account Access | C5: Locked account cannot authenticate until administrative unlock or configured timeout | D5: Player account is in locked state after repeated failures | E5: 1. Attempt login on locked account 2. Review message | F5: locked player account | G5: System blocks access and explains next allowed action without exposing sensitive internals | H5: High | I5: Security | J5: Later | K5: Not Run | L5: Account lockout
A6: WAL-AUTH-004 | B6: Wallet Account Access | C6: Session timeout requires re-authentication before sensitive wallet action | D6: Player is logged in | E6: 1. Stay idle until session timeout 2. Attempt deposit or withdraw | F6: idle authenticated session | G6: System requests re-authentication before sensitive action continues | H6: High | I6: Security | J6: Later | K6: Not Run | L6: Session control
A7: WAL-AUTH-005 | B7: Wallet Account Access | C7: Back button after logout does not reopen wallet balance page | D7: Player has logged out successfully | E7: 1. Log out 2. Click browser Back | F7: logged-out browser session | G7: Protected wallet pages are not accessible without new authentication | H7: High | I7: Security | J7: Yes | K7: Not Run | L7: Post-logout protection
A8: WAL-AUTH-006 | B8: Wallet Account Access | C8: Disabled responsible-gaming account is blocked from wallet access | D8: Player account is disabled or suspended | E8: 1. Attempt login 2. Review result | F8: suspended player account | G8: System denies access and surfaces controlled account-status message | H8: Critical | I8: Negative | J8: Later | K8: Not Run | L8: Restricted access

Sheet 20_Deposit_Flows
A1: Update the Status and Notes columns during execution. Summary KPIs and counts refresh automatically.
A2: TC_ID | B2: Module | C2: Scenario | D2: Preconditions | E2: Steps | F2: Test Data | G2: Expected Result | H2: Priority | I2: Type | J2: Automation Candidate | K2: Status | L2: Notes
A3: DEP-001 | B3: Deposit Flows | C3: Successful card deposit credits player wallet and records transaction | D3: Player is logged in with verified payment method | E3: 1. Open deposit page 2. Enter amount 3. Submit valid card payment | F3: €50 Visa card | G3: Deposit succeeds, wallet balance increases by exact amount, and transaction is logged | H3: Critical | I3: Positive | J3: Yes | K3: Not Run | L3: Core deposit flow
A4: DEP-002 | B4: Deposit Flows | C4: Deposit fails when card authorization is declined | D4: Player is logged in | E4: 1. Attempt deposit with declined card 2. Review balance and history | F4: Declined test card / €50 | G4: System shows failed deposit, wallet balance remains unchanged, and failure is logged | H4: Critical | I4: Negative | J4: Yes | K4: Not Run | L4: Decline handling
A5: DEP-003 | B5: Deposit Flows | C5: Minimum deposit amount validation is enforced | D5: Player is logged in | E5: 1. Attempt deposit below minimum threshold | F5: €1 when minimum is €5 | G5: System blocks submission and explains minimum amount rule | H5: High | I5: Negative | J5: Yes | K5: Not Run | L5: Business rule validation
A6: DEP-004 | B6: Deposit Flows | C6: Duplicate click on deposit submit does not create duplicate credits | D6: Player is logged in with valid payment method | E6: 1. Enter valid deposit 2. Double-click submit or retry during latency | F6: €25 deposit request | G6: System remains idempotent and only one successful deposit is credited | H6: Critical | I6: Integration | J6: Later | K6: Not Run | L6: Idempotency
A7: DEP-005 | B7: Deposit Flows | C7: Deposit history shows completed transaction with reference and timestamp | D7: Successful deposit was completed earlier | E7: 1. Open transaction history 2. Filter by recent deposits | F7: existing successful deposit | G7: History displays correct amount, status, method, and reference for completed deposit | H7: High | I7: Regression | J7: Later | K7: Not Run | L7: History visibility
A8: DEP-006 | B8: Deposit Flows | C8: Daily deposit limit prevents amount above configured threshold | D8: Player has existing deposits near daily limit | E8: 1. Attempt deposit that exceeds remaining daily limit | F8: Deposit causing total > daily limit | G8: System blocks deposit and presents responsible-gaming limit message | H8: Critical | I8: Negative | J8: Later | K8: Not Run | L8: Responsible gaming limit

Sheet 30_Withdrawal_Flows
A1: Update the Status and Notes columns during execution. Summary KPIs and counts refresh automatically.
A2: TC_ID | B2: Module | C2: Scenario | D2: Preconditions | E2: Steps | F2: Test Data | G2: Expected Result | H2: Priority | I2: Type | J2: Automation Candidate | K2: Status | L2: Notes
A3: WDR-001 | B3: Withdrawal Flows | C3: Successful withdrawal debits wallet and creates pending payout record | D3: Player is logged in with sufficient cleared balance and verified payout method | E3: 1. Open withdraw page 2. Enter amount 3. Submit valid withdrawal | F3: €40 withdrawal to verified bank account | G3: Wallet available balance is reduced correctly and payout record is created with pending status | H3: Critical | I3: Positive | J3: Yes | K3: Not Run | L3: Core withdrawal
A4: WDR-002 | B4: Withdrawal Flows | C4: Withdrawal is blocked when amount exceeds available balance | D4: Player is logged in | E4: 1. Attempt withdrawal above available balance | F4: €500 with €100 available | G4: System blocks request and balance remains unchanged | H4: Critical | I4: Negative | J4: Yes | K4: Not Run | L4: Balance validation
A5: WDR-003 | B5: Withdrawal Flows | C5: Withdrawal is blocked when KYC status is incomplete | D5: Player is logged in but verification incomplete | E5: 1. Attempt withdrawal | F5: unverified player / €20 | G5: System blocks withdrawal and prompts verification requirements | H5: Critical | I5: Security | J5: Later | K5: Not Run | L5: KYC dependency
A6: WDR-004 | B6: Withdrawal Flows | C6: Cancellation of pending withdrawal restores available wallet balance once reversal completes | D6: Player has a pending withdrawal eligible for cancel | E6: 1. Cancel pending withdrawal 2. Refresh balance and history | F6: existing pending withdrawal | G6: Cancelled withdrawal is reversed cleanly and funds become available again | H6: High | I6: Integration | J6: Later | K6: Not Run | L6: Reversal handling
A7: WDR-005 | B7: Withdrawal Flows | C7: Withdrawal fees are displayed and posted correctly when applicable | D7: Player is logged in and fee policy applies | E7: 1. Enter withdrawal amount 2. Submit 3. Review ledger | F7: €100 withdrawal with fee policy | G7: Displayed net amount and recorded fee match configured fee rules | H7: Medium | I7: Regression | J7: Later | K7: Not Run | L7: Fee calculation
A8: WDR-006 | B8: Withdrawal Flows | C8: Repeated submission during timeout does not create duplicate withdrawal requests | D8: Player is logged in with sufficient balance | E8: 1. Submit withdrawal 2. Retry during processing delay | F8: €30 withdrawal retried during latency | G8: System creates at most one active withdrawal request | H8: Critical | I8: Negative | J8: Later | K8: Not Run | L8: Duplicate prevention

Sheet 40_Transfer_Refunds
A1: Update the Status and Notes columns during execution. Summary KPIs and counts refresh automatically.
A2: TC_ID | B2: Module | C2: Scenario | D2: Preconditions | E2: Steps | F2: Test Data | G2: Expected Result | H2: Priority | I2: Type | J2: Automation Candidate | K2: Status | L2: Notes
A3: TRF-001 | B3: Transfer & Refunds | C3: Internal wallet transfer between sub-wallets updates both balances consistently | D3: Player account supports cash and bonus wallets | E3: 1. Transfer amount between wallets 2. Review balances | F3: €10 cash to bonus wallet | G3: Source and destination balances update correctly and ledger entries remain balanced | H3: High | I3: Integration | J3: Later | K3: Not Run | L3: Sub-wallet movement
A4: TRF-002 | B4: Transfer & Refunds | C4: Failed game round refund restores original wallet amount exactly once | D4: A failed or cancelled game round exists | E4: 1. Trigger refund flow 2. Review balance and transaction history | F4: cancelled bet refund | G4: Refund amount is restored once and linked to original failed round | H4: Critical | I4: Integration | J4: Later | K4: Not Run | L4: Refund integrity
A5: TRF-003 | B5: Transfer & Refunds | C5: Manual adjustment by authorized operator is visible in audit and player history | D5: Authorized back-office operator exists | E5: 1. Post wallet adjustment 2. Review player history and audit | F5: operator credit +€15 | G5: Adjustment is recorded with reason code, operator identity, and resulting balance | H5: High | I5: Security | J5: Later | K5: Not Run | L5: Adjustment traceability
A6: TRF-004 | B6: Transfer & Refunds | C6: Unauthorized user cannot invoke wallet adjustment API directly | D6: Unauthorized or player-only token available | E6: 1. Call adjustment endpoint without privilege | F6: player token / adjustment payload | G6: System returns authorization failure and no ledger change occurs | H6: Critical | I6: Negative | J6: Yes | K6: Not Run | L6: Privilege enforcement
A7: TRF-005 | B7: Transfer & Refunds | C7: Refund history can be filtered by transaction reference | D7: At least one refunded transaction exists | E7: 1. Open history 2. Search using transaction reference | F7: existing refund reference | G7: Refund entry is returned with correct amount and status | H7: Medium | I7: Positive | J7: Later | K7: Not Run | L7: Searchability

Sheet 50_Balance_Reconciliation
A1: Update the Status and Notes columns during execution. Summary KPIs and counts refresh automatically.
A2: TC_ID | B2: Module | C2: Scenario | D2: Preconditions | E2: Steps | F2: Test Data | G2: Expected Result | H2: Priority | I2: Type | J2: Automation Candidate | K2: Status | L2: Notes
A3: REC-001 | B3: Balance & Reconciliation | C3: Displayed wallet balance matches latest backend ledger total after deposit | D3: Recent deposit exists | E3: 1. Open wallet UI 2. Compare UI balance with backend record | F3: recent successful deposit | G3: Frontend balance matches reconciled backend ledger total | H3: Critical | I3: Integration | J3: Later | K3: Not Run | L3: UI to ledger consistency
A4: REC-002 | B4: Balance & Reconciliation | C4: Pending withdrawal amount is excluded from available balance but remains in total ledger | D4: Pending withdrawal exists | E4: 1. Review available and pending amounts 2. Compare with ledger | F4: account with pending withdrawal | G4: Displayed amounts follow business rules and backend totals remain consistent | H4: High | I4: Regression | J4: Later | K4: Not Run | L4: Available vs pending
A5: REC-003 | B5: Balance & Reconciliation | C5: Transaction history remains chronologically ordered across deposit, bet, refund, and withdrawal actions | D5: Mixed transaction activity exists | E5: 1. Review transaction history 2. Compare timestamps and references | F5: multi-transaction player account | G5: History ordering and running balance are correct across mixed event types | H5: High | I5: Regression | J5: Later | K5: Not Run | L5: History ordering
A6: REC-004 | B6: Balance & Reconciliation | C6: Ledger processing error triggers visible failed status without silent balance corruption | D6: Injected or simulated ledger failure exists | E6: 1. Trigger simulated failure 2. Review UI and logs | F6: simulated ledger exception | G6: Wallet does not show incorrect credit/debit and system surfaces controlled failure status | H6: Critical | I6: Negative | J6: Later | K6: Not Run | L6: Failure containment
A7: REC-005 | B7: Balance & Reconciliation | C7: End-of-day reconciliation report totals match transaction ledger totals for test player set | D7: Reconciliation job can be run against sample data | E7: 1. Run reconciliation 2. Compare totals | F7: sample player dataset | G7: Report totals equal underlying ledger totals and any variance is highlighted | H7: High | I7: Integration | J7: Later | K7: Not Run | L7: Reporting consistency

Sheet 60_Wallet_E2E
A1: Update the Status and Notes columns during execution. Summary KPIs and counts refresh automatically.
A2: TC_ID | B2: Module | C2: Scenario | D2: Preconditions | E2: Steps | F2: Test Data | G2: Expected Result | H2: Priority | I2: Type | J2: Automation Candidate | K2: Status | L2: Notes
A3: WAL-E2E-001 | B3: Wallet End-to-End | C3: Login to deposit to updated balance flow works end-to-end | D3: Verified player account exists | E3: 1. Log in 2. Deposit funds 3. Review new balance and history | F3: verified player / €25 deposit | G3: Player can authenticate, deposit successfully, and see updated balance end-to-end | H3: Critical | I3: E2E | J3: Later | K3: Not Run | L3: Core wallet journey
A4: WAL-E2E-002 | B4: Wallet End-to-End | C4: Deposit to game refund to final balance flow remains consistent end-to-end | D4: Player has funded wallet and game refund scenario | E4: 1. Deposit 2. Trigger cancelled game round 3. Review refund and balance | F4: €20 deposit + cancelled round | G4: Final balance equals opening balance plus deposit plus refund rules without duplication | H4: Critical | I4: E2E | J4: Later | K4: Not Run | L4: Refund lifecycle
A5: WAL-E2E-003 | B5: Wallet End-to-End | C5: Deposit to withdrawal flow enforces KYC and balance rules end-to-end | D5: Player exists with configurable KYC state | E5: 1. Deposit 2. Attempt withdrawal 3. Review outcome | F5: verified and unverified player variants | G5: System enforces KYC and balance logic correctly through full flow | H5: Critical | I5: E2E | J5: Later | K5: Not Run | L5: Compliance-aware wallet flow
A6: WAL-E2E-004 | B6: Wallet End-to-End | C6: Logout and re-login preserves transaction history and latest balance | D6: Player completed prior wallet actions | E6: 1. Perform wallet action 2. Log out 3. Log back in 4. Review wallet | F6: recent wallet transactions | G6: Previously saved wallet data remains visible and accurate after new session | H6: Critical | I6: E2E | J6: Later | K6: Not Run | L6: Session persistence
